{"rabbit_version":"3.8.5","rabbitmq_version":"3.8.5","product_name":"RabbitMQ","product_version":"3.8.5","users":[{"name":"CygnetGSP","password_hash":"SuEdb+5DtacCXmi2iECsK0wR5OdibxtGcWgcfpSIwd1VEt0B","hashing_algorithm":"rabbit_password_hashing_sha256","tags":"monitoring"},{"name":"guest","password_hash":"0A2Ot8EB50CWX7vciUTk54aXzHlY1Uo36t5+6U8OTwIA1QhX","hashing_algorithm":"rabbit_password_hashing_sha256","tags":"administrator"}],"vhosts":[{"name":"dead-letter"},{"name":"Fanout"},{"name":"/"},{"name":"Direct"}],"permissions":[{"user":"guest","vhost":"Fanout","configure":".*","write":".*","read":".*"},{"user":"CygnetGSP","vhost":"/","configure":".*","write":".*","read":".*"},{"user":"CygnetGSP","vhost":"Fanout","configure":".*","write":".*","read":".*"},{"user":"CygnetGSP","vhost":"dead-letter","configure":".*","write":".*","read":".*"},{"user":"CygnetGSP","vhost":"Direct","configure":".*","write":".*","read":".*"},{"user":"guest","vhost":"/","configure":".*","write":".*","read":".*"},{"user":"guest","vhost":"Direct","configure":".*","write":".*","read":".*"},{"user":"guest","vhost":"dead-letter","configure":".*","write":".*","read":".*"}],"topic_permissions":[],"parameters":[],"global_parameters":[{"name":"cluster_name","value":"rabbit@rabbit"},{"name":"internal_cluster_id","value":"rabbitmq-cluster-id-TlHmJqejzbrxXYImh11-Lg"}],"policies":[{"vhost":"/","name":"ha-all","pattern":"","apply-to":"all","definition":{"ha-mode":"all","ha-sync-mode":"automatic"},"priority":0},{"vhost":"dead-letter","name":"ha-all","pattern":"","apply-to":"all","definition":{"ha-mode":"all","ha-sync-mode":"automatic"},"priority":0}],"queues":[{"name":"CygnetGSPConsumerReferenceStatusEngine","vhost":"dead-letter","durable":true,"auto_delete":false,"arguments":{"x-max-priority":9}},{"name":"CygnetGSPConsumerStockStatementEngine","vhost":"dead-letter","durable":true,"auto_delete":false,"arguments":{"x-max-priority":9}},{"name":"CygnetGSPConsumerTaskDetailsEngine","vhost":"dead-letter","durable":true,"auto_delete":false,"arguments":{"x-max-priority":9}},{"name":"CygnetGSPConsumerEWBNotificationsEngine","vhost":"dead-letter","durable":true,"auto_delete":false,"arguments":{"x-max-priority":9}},{"name":"CygnetGSPConsumerReconciliationAnalysisReportEngine","vhost":"dead-letter","durable":true,"auto_delete":false,"arguments":{"x-max-priority":9}},{"name":"CygnetGSPConsumerEWBAS2Engine","vhost":"dead-letter","durable":true,"auto_delete":false,"arguments":{"x-max-priority":9}},{"name":"CygnetGSPConsumerDocumentNotificationsEngine","vhost":"dead-letter","durable":true,"auto_delete":false,"arguments":{"x-max-priority":9}},{"name":"CygnetFAMEConsumerTaxpayerBulkSearchDetailEngine","vhost":"dead-letter","durable":true,"auto_delete":false,"arguments":{"x-max-priority":9}},{"name":"CygnetGSPConsumerEWBDownloadEngine","vhost":"dead-letter","durable":true,"auto_delete":false,"arguments":{"x-max-priority":9}},{"name":"CygnetFAMEConsumerStatementReaderEngine","vhost":"dead-letter","durable":true,"auto_delete":false,"arguments":{"x-max-priority":9}},{"name":"CygnetFAMEConsumerCallbackProcessorEngine","vhost":"dead-letter","durable":true,"auto_delete":false,"arguments":{"x-max-priority":9}},{"name":"CygnetGSPConsumerEWBGetDetailsEngine","vhost":"dead-letter","durable":true,"auto_delete":false,"arguments":{"x-max-priority":9}},{"name":"CygnetFAMEConsumerDownloadGSTINSummaryEngine","vhost":"dead-letter","durable":true,"auto_delete":false,"arguments":{"x-max-priority":9}},{"name":"CygnetGSPConsumerTaxpayerBulkSearchUpdateJobEngine","vhost":"dead-letter","durable":true,"auto_delete":false,"arguments":{"x-max-priority":9}},{"name":"CygnetGSPConsumerGSTSummaryEngine","vhost":"dead-letter","durable":true,"auto_delete":false,"arguments":{"x-max-priority":9}},{"name":"CygnetGSPConsumerEWBAS2ResponseEngine","vhost":"dead-letter","durable":true,"auto_delete":false,"arguments":{"x-max-priority":9}},{"name":"CygnetFAMEConsumerTaxpayerBulkSearchUpdateJobEngine","vhost":"dead-letter","durable":true,"auto_delete":false,"arguments":{"x-max-priority":9}},{"name":"CygnetGSPConsumerEWBUpdateDistanceEngine","vhost":"dead-letter","durable":true,"auto_delete":false,"arguments":{"x-max-priority":9}},{"name":"CygnetGSPConsumerTaxpayerBulkSearchDetailEngine","vhost":"dead-letter","durable":true,"auto_delete":false,"arguments":{"x-max-priority":9}},{"name":"CygnetFAMEConsumerGRCScoreGenerationEngine","vhost":"dead-letter","durable":true,"auto_delete":false,"arguments":{"x-max-priority":9}},{"name":"CygnetGSPConsumerEWBPushToNICEngine","vhost":"dead-letter","durable":true,"auto_delete":false,"arguments":{"x-max-priority":9}},{"name":"CygnetFAMEConsumerDownloadGSTDataEngine","vhost":"dead-letter","durable":true,"auto_delete":false,"arguments":{"x-max-priority":9}},{"name":"CygnetGSPConsumerEWBAS2Engine","vhost":"/","durable":true,"auto_delete":false,"arguments":{"x-max-priority":9}},{"name":"CygnetGSPConsumerReconciliationAnalysisReportEngine","vhost":"/","durable":true,"auto_delete":false,"arguments":{"x-max-priority":9}},{"name":"CygnetFAMEConsumerDownloadGSTDataEngine","vhost":"/","durable":true,"auto_delete":false,"arguments":{"x-max-priority":9}},{"name":"CygnetGSPConsumerTaxpayerBulkSearchUpdateJobEngine","vhost":"/","durable":true,"auto_delete":false,"arguments":{"x-max-priority":9}},{"name":"CygnetFAMEConsumerTaxpayerBulkSearchUpdateJobEngine","vhost":"/","durable":true,"auto_delete":false,"arguments":{"x-max-priority":9}},{"name":"CygnetGSPConsumerEWBNotificationsEngine","vhost":"/","durable":true,"auto_delete":false,"arguments":{"x-max-priority":9}},{"name":"CygnetGSPConsumerTaskDetailsEngine","vhost":"/","durable":true,"auto_delete":false,"arguments":{"x-max-priority":9}},{"name":"CygnetGSPConsumerReferenceStatusEngine","vhost":"/","durable":true,"auto_delete":false,"arguments":{"x-max-priority":9}},{"name":"CygnetGSPConsumerEWBGetDetailsEngine","vhost":"/","durable":true,"auto_delete":false,"arguments":{"x-max-priority":9}},{"name":"CygnetGSPConsumerStockStatementEngine","vhost":"/","durable":true,"auto_delete":false,"arguments":{"x-max-priority":9}},{"name":"CygnetGSPConsumerEWBDownloadEngine","vhost":"/","durable":true,"auto_delete":false,"arguments":{"x-max-priority":9}},{"name":"CygnetGSPConsumerEWBAS2ResponseEngine","vhost":"/","durable":true,"auto_delete":false,"arguments":{"x-max-priority":9}},{"name":"CygnetGSPConsumerEWBPushToNICEngine","vhost":"/","durable":true,"auto_delete":false,"arguments":{"x-max-priority":9}},{"name":"CygnetGSPConsumerGSTSummaryEngine","vhost":"/","durable":true,"auto_delete":false,"arguments":{"x-max-priority":9}},{"name":"CygnetFAMEConsumerTaxpayerBulkSearchDetailEngine","vhost":"/","durable":true,"auto_delete":false,"arguments":{"x-max-priority":9}},{"name":"CygnetGSPConsumerEWBUpdateDistanceEngine","vhost":"/","durable":true,"auto_delete":false,"arguments":{"x-max-priority":9}},{"name":"CygnetFAMEConsumerGRCScoreGenerationEngine","vhost":"/","durable":true,"auto_delete":false,"arguments":{"x-max-priority":9}},{"name":"CygnetFAMEConsumerStatementReaderEngine","vhost":"/","durable":true,"auto_delete":false,"arguments":{"x-max-priority":9}},{"name":"CygnetFAMEConsumerCallbackProcessorEngine","vhost":"/","durable":true,"auto_delete":false,"arguments":{"x-max-priority":9}},{"name":"CygnetGSPConsumerDocumentNotificationsEngine","vhost":"/","durable":true,"auto_delete":false,"arguments":{"x-max-priority":9}},{"name":"CygnetGSPConsumerTaxpayerBulkSearchDetailEngine","vhost":"/","durable":true,"auto_delete":false,"arguments":{"x-max-priority":9}},{"name":"CygnetFAMEConsumerDownloadGSTINSummaryEngine","vhost":"/","durable":true,"auto_delete":false,"arguments":{"x-max-priority":9}},{"name":"Regular.PushPurchaseSummariesToGst","vhost":"Direct","durable":true,"auto_delete":false,"arguments":{"x-max-priority":9}},{"name":"Regular.GenerateAnnexure2Summary","vhost":"Direct","durable":true,"auto_delete":false,"arguments":{"x-max-priority":9}},{"name":"Regular.PushPurchaseDocumentsToGstResponse","vhost":"Direct","durable":true,"auto_delete":false,"arguments":{"x-max-priority":9}},{"name":"EInvoice.DownloadEInvoiceData","vhost":"Direct","durable":true,"auto_delete":false,"arguments":{"x-max-priority":9}},{"name":"Regular.SavePurchaseDocuments","vhost":"Direct","durable":true,"auto_delete":false,"arguments":{"x-max-priority":9}},{"name":"App.InsertLog","vhost":"Direct","durable":true,"auto_delete":false,"arguments":{"x-max-priority":9}},{"name":"Regular.PushSaleDocumentsToGst","vhost":"Direct","durable":true,"auto_delete":false,"arguments":{"x-max-priority":9}},{"name":"EInvoice.PushEInvoiceDocumentsToNic","vhost":"Direct","durable":true,"auto_delete":false,"arguments":{"x-max-priority":9}},{"name":"Regular.ImportRegularSummaries","vhost":"Direct","durable":true,"auto_delete":false,"arguments":{"x-max-priority":9}},{"name":"Regular.PushPurchaseDocumentsToGst","vhost":"Direct","durable":true,"auto_delete":false,"arguments":{"x-max-priority":9}},{"name":"Regular.SaveSaleDocuments","vhost":"Direct","durable":true,"auto_delete":false,"arguments":{"x-max-priority":9}},{"name":"Regular.PushSaleSummariesToGst","vhost":"Direct","durable":true,"auto_delete":false,"arguments":{"x-max-priority":9}},{"name":"App.PostCallbackResponse","vhost":"Direct","durable":true,"auto_delete":false,"arguments":{"x-max-priority":9}},{"name":"Regular.PushSaleSummariesToGstResponse","vhost":"Direct","durable":true,"auto_delete":false,"arguments":{"x-max-priority":9}},{"name":"Taxpayer.ImportDocumentSummaries","vhost":"Direct","durable":true,"auto_delete":false,"arguments":{"x-max-priority":9}},{"name":"Regular.PushPurchaseSummariesToGstResponse","vhost":"Direct","durable":true,"auto_delete":false,"arguments":{"x-max-priority":9}},{"name":"Regular.ImportRegularDocuments","vhost":"Direct","durable":true,"auto_delete":false,"arguments":{"x-max-priority":9}},{"name":"Api.UpdateStatistic","vhost":"Direct","durable":true,"auto_delete":false,"arguments":{"x-max-priority":9}},{"name":"Regular.CheckPushActionToGstStatus","vhost":"Direct","durable":true,"auto_delete":false,"arguments":{"x-max-priority":9}},{"name":"Gst.DownloadGstData","vhost":"Direct","durable":true,"auto_delete":false,"arguments":{"x-max-priority":9}},{"name":"Regular.GenerateAnnexure1Summary","vhost":"Direct","durable":true,"auto_delete":false,"arguments":{"x-max-priority":9}},{"name":"EInvoice.PushCancelEInvoiceDocumentsToNic","vhost":"Direct","durable":true,"auto_delete":false,"arguments":{"x-max-priority":9}},{"name":"EInvoice.PushCancelDocumentsToNic","vhost":"Direct","durable":true,"auto_delete":false,"arguments":{"x-max-priority":9}},{"name":"Regular.SavePurchaseSummaries","vhost":"Direct","durable":true,"auto_delete":false,"arguments":{"x-max-priority":9}},{"name":"Regular.InsertPurchaseDocumentReco","vhost":"Direct","durable":true,"auto_delete":false,"arguments":{"x-max-priority":9}},{"name":"Api.InsertTransactionLog","vhost":"Direct","durable":true,"auto_delete":false,"arguments":{"x-max-priority":9}},{"name":"Gst.GenerateItcSummary","vhost":"Direct","durable":true,"auto_delete":false,"arguments":{"x-max-priority":9}},{"name":"Regular.GenerateItcSummary","vhost":"Direct","durable":true,"auto_delete":false,"arguments":{"x-max-priority":9}},{"name":"EInvoice.DownloadEInvoiceDocumentFromNic","vhost":"Direct","durable":true,"auto_delete":false,"arguments":{"x-max-priority":9}},{"name":"Regular.GenerateReturn1Summary","vhost":"Direct","durable":true,"auto_delete":false,"arguments":{"x-max-priority":9}},{"name":"Regular.GenerateOverview","vhost":"Direct","durable":true,"auto_delete":false,"arguments":{"x-max-priority":9}},{"name":"Gst.GenerateAnnexure1Summary","vhost":"Direct","durable":true,"auto_delete":false,"arguments":{"x-max-priority":9}},{"name":"Gst.GenerateAnnexure2Summary","vhost":"Direct","durable":true,"auto_delete":false,"arguments":{"x-max-priority":9}},{"name":"Taxpayer.ImportTaxpayerDocuments","vhost":"Direct","durable":true,"auto_delete":false,"arguments":{"x-max-priority":9}},{"name":"Regular.PushActionToGst","vhost":"Direct","durable":true,"auto_delete":false,"arguments":{"x-max-priority":9}},{"name":"Regular.PushSaleDocumentsToGstResponse","vhost":"Direct","durable":true,"auto_delete":false,"arguments":{"x-max-priority":9}},{"name":"EInvoice.PushDocumentsToNic","vhost":"Direct","durable":true,"auto_delete":false,"arguments":{"x-max-priority":9}},{"name":"Regular.GenerateSaleSummaries","vhost":"Direct","durable":true,"auto_delete":false,"arguments":{"x-max-priority":9}},{"name":"Taxpayer.ImportDocuments","vhost":"Direct","durable":true,"auto_delete":false,"arguments":{"x-max-priority":9}},{"name":"Regular.SaveSaleSummaries","vhost":"Direct","durable":true,"auto_delete":false,"arguments":{"x-max-priority":9}},{"name":"Gst.GenerateReturn1Summary","vhost":"Direct","durable":true,"auto_delete":false,"arguments":{"x-max-priority":9}},{"name":"Regular.GeneratePurchaseSummaries","vhost":"Direct","durable":true,"auto_delete":false,"arguments":{"x-max-priority":9}}],"exchanges":[{"name":"Queue.BroadcastMessage","vhost":"Fanout","type":"fanout","durable":false,"auto_delete":false,"internal":false,"arguments":{}},{"name":"DelayMessage","vhost":"Direct","type":"x-delayed-message","durable":true,"auto_delete":false,"internal":false,"arguments":{"x-delayed-type":"direct"}}],"bindings":[{"source":"DelayMessage","vhost":"Direct","destination":"Api.InsertTransactionLog","destination_type":"queue","routing_key":"Api.InsertTransactionLog","arguments":{}},{"source":"DelayMessage","vhost":"Direct","destination":"Api.UpdateStatistic","destination_type":"queue","routing_key":"Api.UpdateStatistic","arguments":{}},{"source":"DelayMessage","vhost":"Direct","destination":"App.InsertLog","destination_type":"queue","routing_key":"App.InsertLog","arguments":{}},{"source":"DelayMessage","vhost":"Direct","destination":"App.PostCallbackResponse","destination_type":"queue","routing_key":"App.PostCallbackResponse","arguments":{}},{"source":"DelayMessage","vhost":"Direct","destination":"EInvoice.DownloadEInvoiceData","destination_type":"queue","routing_key":"EInvoice.DownloadEInvoiceData","arguments":{}},{"source":"DelayMessage","vhost":"Direct","destination":"EInvoice.DownloadEInvoiceDocumentFromNic","destination_type":"queue","routing_key":"EInvoice.DownloadEInvoiceDocumentFromNic","arguments":{}},{"source":"DelayMessage","vhost":"Direct","destination":"EInvoice.PushCancelDocumentsToNic","destination_type":"queue","routing_key":"EInvoice.PushCancelDocumentsToNic","arguments":{}},{"source":"DelayMessage","vhost":"Direct","destination":"EInvoice.PushCancelEInvoiceDocumentsToNic","destination_type":"queue","routing_key":"EInvoice.PushCancelEInvoiceDocumentsToNic","arguments":{}},{"source":"DelayMessage","vhost":"Direct","destination":"EInvoice.PushDocumentsToNic","destination_type":"queue","routing_key":"EInvoice.PushDocumentsToNic","arguments":{}},{"source":"DelayMessage","vhost":"Direct","destination":"EInvoice.PushEInvoiceDocumentsToNic","destination_type":"queue","routing_key":"EInvoice.PushEInvoiceDocumentsToNic","arguments":{}},{"source":"DelayMessage","vhost":"Direct","destination":"Gst.DownloadGstData","destination_type":"queue","routing_key":"Gst.DownloadGstData","arguments":{}},{"source":"DelayMessage","vhost":"Direct","destination":"Gst.GenerateAnnexure1Summary","destination_type":"queue","routing_key":"Gst.GenerateAnnexure1Summary","arguments":{}},{"source":"DelayMessage","vhost":"Direct","destination":"Gst.GenerateAnnexure2Summary","destination_type":"queue","routing_key":"Gst.GenerateAnnexure2Summary","arguments":{}},{"source":"DelayMessage","vhost":"Direct","destination":"Gst.GenerateItcSummary","destination_type":"queue","routing_key":"Gst.GenerateItcSummary","arguments":{}},{"source":"DelayMessage","vhost":"Direct","destination":"Gst.GenerateReturn1Summary","destination_type":"queue","routing_key":"Gst.GenerateReturn1Summary","arguments":{}},{"source":"DelayMessage","vhost":"Direct","destination":"Regular.CheckPushActionToGstStatus","destination_type":"queue","routing_key":"Regular.CheckPushActionToGstStatus","arguments":{}},{"source":"DelayMessage","vhost":"Direct","destination":"Regular.GenerateAnnexure1Summary","destination_type":"queue","routing_key":"Regular.GenerateAnnexure1Summary","arguments":{}},{"source":"DelayMessage","vhost":"Direct","destination":"Regular.GenerateAnnexure2Summary","destination_type":"queue","routing_key":"Regular.GenerateAnnexure2Summary","arguments":{}},{"source":"DelayMessage","vhost":"Direct","destination":"Regular.GenerateItcSummary","destination_type":"queue","routing_key":"Regular.GenerateItcSummary","arguments":{}},{"source":"DelayMessage","vhost":"Direct","destination":"Regular.GenerateOverview","destination_type":"queue","routing_key":"Regular.GenerateOverview","arguments":{}},{"source":"DelayMessage","vhost":"Direct","destination":"Regular.GeneratePurchaseSummaries","destination_type":"queue","routing_key":"Regular.GeneratePurchaseSummaries","arguments":{}},{"source":"DelayMessage","vhost":"Direct","destination":"Regular.GenerateReturn1Summary","destination_type":"queue","routing_key":"Regular.GenerateReturn1Summary","arguments":{}},{"source":"DelayMessage","vhost":"Direct","destination":"Regular.GenerateSaleSummaries","destination_type":"queue","routing_key":"Regular.GenerateSaleSummaries","arguments":{}},{"source":"DelayMessage","vhost":"Direct","destination":"Regular.ImportRegularDocuments","destination_type":"queue","routing_key":"Regular.ImportRegularDocuments","arguments":{}},{"source":"DelayMessage","vhost":"Direct","destination":"Regular.ImportRegularSummaries","destination_type":"queue","routing_key":"Regular.ImportRegularSummaries","arguments":{}},{"source":"DelayMessage","vhost":"Direct","destination":"Regular.InsertPurchaseDocumentReco","destination_type":"queue","routing_key":"Regular.InsertPurchaseDocumentReco","arguments":{}},{"source":"DelayMessage","vhost":"Direct","destination":"Regular.PushActionToGst","destination_type":"queue","routing_key":"Regular.PushActionToGst","arguments":{}},{"source":"DelayMessage","vhost":"Direct","destination":"Regular.PushPurchaseDocumentsToGst","destination_type":"queue","routing_key":"Regular.PushPurchaseDocumentsToGst","arguments":{}},{"source":"DelayMessage","vhost":"Direct","destination":"Regular.PushPurchaseDocumentsToGstResponse","destination_type":"queue","routing_key":"Regular.PushPurchaseDocumentsToGstResponse","arguments":{}},{"source":"DelayMessage","vhost":"Direct","destination":"Regular.PushPurchaseSummariesToGst","destination_type":"queue","routing_key":"Regular.PushPurchaseSummariesToGst","arguments":{}},{"source":"DelayMessage","vhost":"Direct","destination":"Regular.PushPurchaseSummariesToGstResponse","destination_type":"queue","routing_key":"Regular.PushPurchaseSummariesToGstResponse","arguments":{}},{"source":"DelayMessage","vhost":"Direct","destination":"Regular.PushSaleDocumentsToGst","destination_type":"queue","routing_key":"Regular.PushSaleDocumentsToGst","arguments":{}},{"source":"DelayMessage","vhost":"Direct","destination":"Regular.PushSaleDocumentsToGstResponse","destination_type":"queue","routing_key":"Regular.PushSaleDocumentsToGstResponse","arguments":{}},{"source":"DelayMessage","vhost":"Direct","destination":"Regular.PushSaleSummariesToGst","destination_type":"queue","routing_key":"Regular.PushSaleSummariesToGst","arguments":{}},{"source":"DelayMessage","vhost":"Direct","destination":"Regular.PushSaleSummariesToGstResponse","destination_type":"queue","routing_key":"Regular.PushSaleSummariesToGstResponse","arguments":{}},{"source":"DelayMessage","vhost":"Direct","destination":"Regular.SavePurchaseDocuments","destination_type":"queue","routing_key":"Regular.SavePurchaseDocuments","arguments":{}},{"source":"DelayMessage","vhost":"Direct","destination":"Regular.SavePurchaseSummaries","destination_type":"queue","routing_key":"Regular.SavePurchaseSummaries","arguments":{}},{"source":"DelayMessage","vhost":"Direct","destination":"Regular.SaveSaleDocuments","destination_type":"queue","routing_key":"Regular.SaveSaleDocuments","arguments":{}},{"source":"DelayMessage","vhost":"Direct","destination":"Regular.SaveSaleSummaries","destination_type":"queue","routing_key":"Regular.SaveSaleSummaries","arguments":{}},{"source":"DelayMessage","vhost":"Direct","destination":"Taxpayer.ImportDocumentSummaries","destination_type":"queue","routing_key":"Taxpayer.ImportDocumentSummaries","arguments":{}},{"source":"DelayMessage","vhost":"Direct","destination":"Taxpayer.ImportDocuments","destination_type":"queue","routing_key":"Taxpayer.ImportDocuments","arguments":{}},{"source":"DelayMessage","vhost":"Direct","destination":"Taxpayer.ImportTaxpayerDocuments","destination_type":"queue","routing_key":"Taxpayer.ImportTaxpayerDocuments","arguments":{}}]}